skyline/__init__.py
skyline/errors.py
skyline/rl_protos.py
skyline/alg/__init__.py
skyline/alg/bcst_epsilon_tcs_rl.py
skyline/alg/monte_carlo.py
skyline/alg/random_rl.py
skyline/lab/__init__.py
skyline/lab/bcst_tc_env.py
skyline/lab/gridworld_env.py
skyline/lab/gridworld_utils.py
skyline_rl_lab-0.0.1.2.dist-info/LICENSE.md
skyline_rl_lab-0.0.1.2.dist-info/METADATA
skyline_rl_lab-0.0.1.2.dist-info/WHEEL
skyline_rl_lab-0.0.1.2.dist-info/top_level.txt
skyline_rl_lab-0.0.1.2.dist-info/RECORD
