Metadata-Version: 2.1
Name: skyline-rl-lab
Version: 0.0.1.2
Summary: A package to provide RL capability in tasks.
Home-page: https://github.com/google/skyline_rl_lab
Author: John Lee
Author-email: puremonkey2007@gmail.com
License: MIT License
Classifier: Development Status :: 1 - Planning
Classifier: Intended Audience :: Science/Research
Classifier: License :: OSI Approved :: MIT License
Classifier: Operating System :: POSIX :: Linux
Classifier: Programming Language :: Python :: 3.8
Classifier: Programming Language :: Python :: 3.9
Classifier: Programming Language :: Python :: 3.10
Classifier: Programming Language :: Python :: 3.11
License-File: LICENSE.md
Requires-Dist: contourpy ==1.2.1
Requires-Dist: cycler ==0.12.1
Requires-Dist: fonttools ==4.53.1
Requires-Dist: immutabledict ==4.2.0
Requires-Dist: kiwisolver ==1.4.5
Requires-Dist: matplotlib ==3.9.2
Requires-Dist: numpy ==2.0.1
Requires-Dist: packaging ==24.1
Requires-Dist: pillow ==10.4.0
Requires-Dist: prettytable ==3.11.0
Requires-Dist: pyparsing ==3.1.2
Requires-Dist: python-dateutil ==2.9.0.post0
Requires-Dist: six ==1.16.0
Requires-Dist: tqdm ==4.66.5
Requires-Dist: wcwidth ==0.2.13
